torchgraph/__init__.py
torchgraph-0.0.0.dist-info/METADATA
torchgraph-0.0.0.dist-info/WHEEL
torchgraph-0.0.0.dist-info/RECORD
